src/__init__.py
src/cli/__init__.py
src/cli/main.py
src/core/__init__.py
src/core/nbt_file.py
src/core/nbt_path.py
src/core/nbt_types.py
src/core/operations.py
src/utils/__init__.py
src/utils/binary.py
src/utils/i18n.py
minecraft_nbt_editor-0.3.0.dist-info/METADATA
minecraft_nbt_editor-0.3.0.dist-info/WHEEL
minecraft_nbt_editor-0.3.0.dist-info/entry_points.txt
minecraft_nbt_editor-0.3.0.dist-info/licenses/LICENSE
minecraft_nbt_editor-0.3.0.dist-info/RECORD
