Metadata-Version: 2.4
Name: minecraft-nbt-editor
Version: 0.3.0
Summary: A Python-based Minecraft NBT editor supporting Bedrock editions
Project-URL: Homepage, https://github.com/geniusshiun/minecraft-nbt-editor
Project-URL: Repository, https://github.com/geniusshiun/minecraft-nbt-editor
Project-URL: Issues, https://github.com/geniusshiun/minecraft-nbt-editor/issues
Author-email: geniusshiun <geniusshiun@example.com>
License: MIT
License-File: LICENSE
Keywords: bedrock,editor,java,minecraft,nbt
Classifier: Development Status :: 3 - Alpha
Classifier: Intended Audience :: Developers
Classifier: License :: OSI Approved :: MIT License
Classifier: Operating System :: OS Independent
Classifier: Programming Language :: Python :: 3
Classifier: Programming Language :: Python :: 3.8
Classifier: Programming Language :: Python :: 3.9
Classifier: Programming Language :: Python :: 3.10
Classifier: Programming Language :: Python :: 3.11
Classifier: Programming Language :: Python :: 3.12
Classifier: Topic :: Games/Entertainment
Classifier: Topic :: Software Development :: Libraries :: Python Modules
Requires-Python: >=3.8
Requires-Dist: click>=8.0.0
Requires-Dist: rich>=13.0.0
Requires-Dist: tabulate>=0.9.0
Provides-Extra: dev
Requires-Dist: black>=23.0.0; extra == 'dev'
Requires-Dist: flake8>=6.0.0; extra == 'dev'
Requires-Dist: mypy>=1.0.0; extra == 'dev'
Requires-Dist: pre-commit>=3.0.0; extra == 'dev'
Requires-Dist: pytest-cov>=4.0.0; extra == 'dev'
Requires-Dist: pytest>=7.0.0; extra == 'dev'
